[
  {
    "id": 1,
    "name": "Jenny Chan",
    "department": "Accounting",
    "grade": "B1",
    "2022--01 10:10:01": "P",
    "2": "P",
    "3": "P",
    "4": "P",
    "5": "P",
    "6": "P",
    "7": "P",
    "8": "P",
    "9": "P",
    "10": "P",
    "11": "P",
    "12": "P",
    "13": "P",
    "14": "P",
    "15": "P",
    "16": "P",
    "17": "P",
    "18": "P",
    "19": "P",
    "20": "P",
    "21": "P",
    "22": "P",
    "23": "P",
    "24": "P",
    "25": "P",
    "26": "P",
    "27": "P",
    "28": "P",
    "29": "P",
    "30": "P",
    "31": "P"
  },
  {
    "id": 2,
    "name": "Jessica warren",
    "department": "Finance",
    "grade": "B1",
    "1": "P",
    "2": "P",
    "3": "P",
    "4": "P",
    "5": "P",
    "6": "P",
    "7": "P",
    "8": "A",
    "9": "A",
    "10": "A",
    "11": "A",
    "12": "P",
    "13": "P",
    "14": "P",
    "15": "P",
    "16": "P",
    "17": "P",
    "18": "P",
    "19": "P",
    "20": "P",
    "21": "P",
    "22": "P",
    "23": "P",
    "24": "P",
    "25": "P",
    "26": "P",
    "27": "P",
    "28": "P",
    "29": "P",
    "30": "P",
    "31": "P"
  },
  {
    "id": 3,
    "name": "Tony Frank",
    "department": "IT",
    "grade": "B2",
    "1": "P",
    "2": "P",
    "3": "P",
    "4": "P",
    "5": "P",
    "6": "P",
    "7": "P",
    "8": "A",
    "9": "A",
    "10": "A",
    "11": "A",
    "12": "P",
    "13": "P",
    "14": "P",
    "15": "P",
    "16": "P",
    "17": "P",
    "18": "P",
    "19": "L",
    "20": "L",
    "21": "P",
    "22": "P",
    "23": "P",
    "24": "P",
    "25": "P",
    "26": "L",
    "27": "P",
    "28": "P",
    "29": "P",
    "30": "P",
    "31": "P"
  },
  {
    "id": 4,
    "name": "Jeremy Clark",
    "department": "Human Resources",
    "grade": "C2",
    "1": "P",
    "2": "P",
    "3": "P",
    "4": "P",
    "5": "P",
    "6": "P",
    "7": "R",
    "8": "R",
    "9": "R",
    "10": "P",
    "11": "P",
    "12": "P",
    "13": "P",
    "14": "P",
    "15": "P",
    "16": "P",
    "17": "P",
    "18": "A",
    "19": "P",
    "20": "P",
    "21": "A",
    "22": "P",
    "23": "P",
    "24": "P",
    "25": "L",
    "26": "P",
    "27": "P",
    "28": "P",
    "29": "P",
    "30": "P",
    "31": "P"
  },
  {
    "id": 5,
    "name": "Raymond Edwards",
    "department": "Operation",
    "grade": "C2",
    "1": "P",
    "2": "P",
    "3": "P",
    "4": "P",
    "5": "P",
    "6": "P",
    "7": "R",
    "8": "R",
    "9": "R",
    "10": "P",
    "11": "P",
    "12": "P",
    "13": "P",
    "14": "P",
    "15": "P",
    "16": "P",
    "17": "P",
    "18": "A",
    "19": "P",
    "20": "P",
    "21": "A",
    "22": "P",
    "23": "P",
    "24": "P",
    "25": "L",
    "26": "P",
    "27": "P",
    "28": "P",
    "29": "P",
    "30": "P",
    "31": "P"
  },
  {
    "id": 6,
    "name": "James Siu",
    "department": "Marketing",
    "grade": "A1",
    "1": "P",
    "2": "P",
    "3": "P",
    "4": "P",
    "5": "P",
    "6": "P",
    "7": "R",
    "8": "R",
    "9": "R",
    "10": "P",
    "11": "P",
    "12": "P",
    "13": "P",
    "14": "P",
    "15": "P",
    "16": "P",
    "17": "P",
    "18": "A",
    "19": "P",
    "20": "P",
    "21": "A",
    "22": "P",
    "23": "P",
    "24": "P",
    "25": "L",
    "26": "P",
    "27": "P",
    "28": "P",
    "29": "P",
    "30": "P",
    "31": "P"
  }
]
